Easy_Coral/EasyAI.py
Easy_Coral/EasyCamera.py
Easy_Coral/__init__.py
Easy_Coral/test.py
Easy_Coral/models/face_labels.txt
Easy_Coral/models/field_labels.txt
Easy_Coral/models/imagenet_labels.txt
Easy_Coral/models/mobilenet_ssd_v2_face_quant_postprocess_edgetpu.tflite
Easy_Coral/models/mobilenet_v2_1.0_224_quant_edgetpu.tflite
Easy_Coral/models/mobilenet_v2_edgetpu_red.tflite
Easy_Coral-0.1.6.dist-info/LICENSE
Easy_Coral-0.1.6.dist-info/METADATA
Easy_Coral-0.1.6.dist-info/WHEEL
Easy_Coral-0.1.6.dist-info/top_level.txt
Easy_Coral-0.1.6.dist-info/RECORD
