Metadata-Version: 2.1
Name: Easy-Coral
Version: 0.1.6
Summary: Google Coral AI and Camera Manager
Home-page: UNKNOWN
Author: James Warszycki, Devin Willis
Author-email: jwarszycki2017@fau.edu
License: UNKNOWN
Platform: UNKNOWN
Requires-Python: >=3.6
